CHANGES.md
LICENSE
MANIFEST.in
README.md
requirements.txt
setup.py
gitpress/__init__.py
gitpress/command.py
gitpress/default_config.py
gitpress/pipeline.py
gitpress/runner.py
gitpress/server.py
gitpress.egg-info/PKG-INFO
gitpress.egg-info/SOURCES.txt
gitpress.egg-info/dependency_links.txt
gitpress.egg-info/entry_points.txt
gitpress.egg-info/not-zip-safe
gitpress.egg-info/requires.txt
gitpress.egg-info/top_level.txt
gitpress/static/reset.css
gitpress/static/style.css
gitpress/templates/base.html
gitpress/templates/index.html
gitpress/templates/page.html