Metadata-Version: 1.0
Name: gitpress
Version: 0.3
Summary: Blissful blogging for hackers.
Home-page: http://github.com/joeyespo/gitpress
Author: Joe Esposito
Author-email: joe@joeyespo.com
License: MIT
Platform: any
